wolfsoftware/pushover/__init__.py
wolfsoftware/pushover/exceptions.py
wolfsoftware/pushover/pushover.py
wolfsoftware.pushover-0.1.1.dist-info/LICENSE.md
wolfsoftware.pushover-0.1.1.dist-info/METADATA
wolfsoftware.pushover-0.1.1.dist-info/WHEEL
wolfsoftware.pushover-0.1.1.dist-info/top_level.txt
wolfsoftware.pushover-0.1.1.dist-info/RECORD
