Metadata-Version: 2.1
Name: wolfsoftware.pushover
Version: 0.1.1
Summary: A package for sending messages via Pushover.
Home-page: https://github.com/NotificationsToolbox/pushover-package
Author: Wolf Software
Author-email: pypi@wolfsoftware.com
License: MIT
Project-URL: Source, https://github.com/NotificationsToolbox/pushover-package
Project-URL: Tracker, https://github.com/NotificationsToolbox/pushover-package/issues/
Project-URL: Documentation, https://github.com/NotificationsToolbox/pushover-package
Project-URL: Sponsor, https://github.com/sponsors/WolfSoftware
Keywords: python,pushover
Classifier: Development Status :: 4 - Beta
Classifier: Environment :: Console
Classifier: Intended Audience :: Developers
Classifier: Intended Audience :: System Administrators
Classifier: License :: OSI Approved :: MIT License
Classifier: Programming Language :: Python :: 3
Classifier: Programming Language :: Python :: 3.9
Classifier: Programming Language :: Python :: 3.10
Classifier: Programming Language :: Python :: 3.11
Classifier: Programming Language :: Python :: 3.12
Classifier: Operating System :: OS Independent
Classifier: Topic :: Software Development
Requires-Python: >=3.9
License-File: LICENSE.md
Requires-Dist: requests ==2.32.3
